<?xml version="1.0" encoding="UTF-8"?>
<singlesku>
    <appList>
        <appInfo>
            <package>com.microsoft.office.officehubrow</package>
        </appInfo>
        <appInfo>
            <package>com.microsoft.skydrive</package>
        </appInfo>
        <appInfo>
            <package>com.sec.android.app.popupcalculator</package>
        </appInfo>
        <appInfo>
            <package>com.sec.android.app.shealth</package>
        </appInfo>
        <appInfo>
            <package>com.sec.android.app.sbrowser</package>
        </appInfo>
        <appInfo>
            <package>com.sec.android.app.voicenote</package>
        </appInfo>
        <appInfo>
            <package>com.samsung.android.email.provider</package>
        </appInfo>
        <appInfo>
            <package>com.samsung.android.app.notes</package>
        </appInfo>
        <appInfo>
            <package>com.samsung.android.app.notes.addons</package>
        </appInfo>
        <appInfo>
            <package>com.samsung.android.voc</package>
        </appInfo>
        <appInfo>
            <package>com.samsung.android.oneconnect</package>
        </appInfo>
        <appInfo>
            <package>com.samsung.android.spay</package>
        </appInfo>
        <appInfo>
            <package>com.samsung.android.app.watchmanager</package>
        </appInfo>
        <appInfo>
            <package>com.google.android.apps.tachyon</package>
        </appInfo>
        <appInfo>
            <package>com.google.android.apps.docs</package>
        </appInfo>
        <appInfo>
            <package>com.google.android.videos</package>
        </appInfo>
        <appInfo>
            <package>com.google.android.music</package>
        </appInfo>
        <appInfo>
            <package>com.google.android.apps.photos</package>
        </appInfo>
        <appInfo>
            <package>uplus.membership</package>
        </appInfo>
        <appInfo>
            <package>com.lguplus.navi</package>
        </appInfo>
        <appInfo>
            <package>com.estsoft.alyac</package>
            <module>LGUAlYac_Erasable</module>
        </appInfo>
        <appInfo>
            <package>com.uplus.musicshow</package>
        </appInfo>
        <appInfo>
            <package>com.uplus.datacharge</package>
        </appInfo>
        <appInfo>
            <package>com.whox2.lguplus</package>
        </appInfo>
        <appInfo>
            <package>com.lguplus.homeiot</package>
        </appInfo>
        <appInfo>
            <package>com.ktmusic.geniemusic</package>
            <module>LGUGenie_Erasable</module>
        </appInfo>
        <appInfo>
            <package>lgt.call</package>
        </appInfo>
        <appInfo>
            <package>com.uplus.baseballhdtv</package>
        </appInfo>
        <appInfo>
            <package>com.lgu</package>
        </appInfo>
        <appInfo>
            <package>com.uplus.ugolf</package>
        </appInfo>
        <appInfo>
            <package>com.lguplus.smartotp</package>
        </appInfo>
        <appInfo>
            <package>lg.uplusbox</package>
        </appInfo>
        <appInfo>
            <package>com.uplus.onphone</package>
        </appInfo>
        <appInfo>
            <package>com.sec.android.app.kidshome</package>
        </appInfo>
        <appInfo>
            <package>com.samsung.sree</package>
        </appInfo>
        <appInfo>
            <package>com.samsung.android.galaxy</package>
        </appInfo>
    </appList>
</singlesku>
